spacy_jptdp/__init__.py
spacy_jptdp/decoder.py
spacy_jptdp/jPTDP.py
spacy_jptdp/learner.py
spacy_jptdp/mnnl.py
spacy_jptdp/spacy.py
spacy_jptdp/utils.py
spacy_jptdp-0.7.2.dist-info/LICENSE.txt
spacy_jptdp-0.7.2.dist-info/METADATA
spacy_jptdp-0.7.2.dist-info/WHEEL
spacy_jptdp-0.7.2.dist-info/top_level.txt
spacy_jptdp-0.7.2.dist-info/RECORD
