Metadata-Version: 2.1
Name: spacy-jptdp
Version: 0.7.2
Summary: jPTDP wrapper for spaCy
Home-page: https://github.com/KoichiYasuoka/spaCy-jPTDP
Author: Koichi Yasuoka
Author-email: yasuoka@kanji.zinbun.kyoto-u.ac.jp
License: GPL
Project-URL: jPTDP, https://github.com/datquocnguyen/jPTDP
Project-URL: Source, https://github.com/KoichiYasuoka/spaCy-jPTDP
Project-URL: Tracker, https://github.com/KoichiYasuoka/spaCy-jPTDP/issues
Keywords: NLP jPTDP spaCy
Classifier: License :: OSI Approved :: GNU General Public License (GPL)
Classifier: Programming Language :: Python :: 3
Classifier: Operating System :: OS Independent
Classifier: Topic :: Text Processing :: Linguistic
Requires-Python: >=3.6
License-File: LICENSE.txt
Requires-Dist: deplacy (>=2.1.0)
Requires-Dist: dyNET (>=2.0.3)
Requires-Dist: numpy (<2)
Requires-Dist: spacy (>=2.3.0)
